{
  "dependencies": [
    "0_steel"
  ],
  "tasks": {
    "zcx": {
      "type": "heracles:item",
      "item": "gtceu:hp_steam_compressor",
      "amount": 1,
      "collection": "AUTOMATIC"
    }
  },
  "rewards": {
    "se": {
      "icon": {
        "item": {
          "id": "minecraft:bundle",
          "count": 1
        },
        "type": "heracles:item"
      },
      "loot_table": "qilby:rewards/steam",
      "type": "heracles:loottable"
    }
  },
  "display": {
    "subtitle": {
      "translate": "Better steam machines [OPTIONAL]"
    },
    "description": [
      ""
    ],
    "groups": {
      "0 - Create & Steam": {
        "position": [
          75,
          100
        ]
      }
    },
    "icon": {
      "item": {
        "id": "gtceu:hp_steam_compressor",
        "count": 1
      },
      "type": "heracles:item"
    },
    "icon_background": "heracles:textures/gui/quest_backgrounds/diamonds.png",
    "title": {
      "translate": "High Pressure Compressor"
    }
  },
  "settings": {
    "showDependencyArrow": true,
    "repeatable": false,
    "autoClaimRewards": false,
    "individual_progress": false,
    "hidden": "LOCKED",
    "unlockNotification": false
  }
}